easyvalidate/__init__.py
easyvalidate/_version.py
easyvalidate/exceptions.py
easyvalidate/warnings.py
easyvalidate/_helpers/__init__.py
easyvalidate/_helpers/arguments.py
easyvalidate/_helpers/type_info.py
easyvalidate/type_validation/__init__.py
easyvalidate/type_validation/typehints/__init__.py
easyvalidate/type_validation/typehints/arg_validators.py
easyvalidate/type_validation/typehints/decorator.py
easyvalidate/type_validation/typehints/function_validator.py
easyvalidate/value_validation/__init__.py
easyvalidate/value_validation/containment.py
easyvalidate/value_validation/expression.py
easyvalidate/value_validation/lazy_evaluation.py
easyvalidate/value_validation/range.py
easyvalidate-0.0.2.dist-info/LICENSE
easyvalidate-0.0.2.dist-info/METADATA
easyvalidate-0.0.2.dist-info/WHEEL
easyvalidate-0.0.2.dist-info/top_level.txt
easyvalidate-0.0.2.dist-info/RECORD
