Metadata-Version: 2.1
Name: easyvalidate
Version: 0.0.2
Summary: Validation utilities
Home-page: https://github.com/mtmk-ee/easyvalidate
Author: Mitchell Matsumori-Kelly
Project-URL: homepage, https://github.com/mtmk-ee/easyvalidate
Project-URL: documentation, https://easyvalidate.readthedocs.io/en/latest/
Project-URL: repository, https://github.com/mtmk-ee/easyvalidate.git
Classifier: Development Status :: 3 - Alpha
Classifier: Environment :: Console
Classifier: Programming Language :: Python :: 3
Classifier: Intended Audience :: Developers
Classifier: License :: OSI Approved :: MIT License
Classifier: Operating System :: OS Independent
Requires-Python: >=3.8
License-File: LICENSE
Provides-Extra: dev
Requires-Dist: pytest ; extra == 'dev'
Requires-Dist: pytest-mock ; extra == 'dev'
